AutoNode/__init__.py
AutoNode/common.py
AutoNode/daemon.py
AutoNode/exceptions.py
AutoNode/initialize.py
AutoNode/monitor.py
AutoNode/node.py
AutoNode/passphrase.py
AutoNode/util.py
AutoNode/validator.py
AutoNode-1.0.5.dist-info/LICENSE
AutoNode-1.0.5.dist-info/METADATA
AutoNode-1.0.5.dist-info/WHEEL
AutoNode-1.0.5.dist-info/top_level.txt
AutoNode-1.0.5.dist-info/RECORD
